{
    "ECF" : {
        "Encabezado": {
            "Version": "1.0",
            "IdDoc": {
                "TipoeCF": "33",
                "eNCF": "E330000000001",
                "FechaVencimientoSecuencia": "31-12-2025",
                "TipoIngresos": "01",
                "TipoPago": "1",
                "TablaFormasPago": {
                    "FormaDePago" : [
                    {
                        "FormaPago": 1,	
                        "MontoPago": "400000.00"
                    }]
                }},
            "Emisor":{
                "RNCEmisor": "130939616",
                "RazonSocialEmisor": "DOCUMENTOS ELECTRONICOS DE 02",
                "NombreComercial": "DOCUMENTOS ELECTRONICOS DE 02",
                "DireccionEmisor": "AVE. ISABEL AGUIAR NO. 269, ZONA INDUSTRIAL DE HERRERA",
                "Municipio": "010100",
                "Provincia": "010000",
                "TablaTelefonoEmisor": {
                    "TelefonoEmisor" : [
                    "809-472-7676",
                    "809-491-1918"]
                },
                "CorreoEmisor": "DOCUMENTOSELECTRONICOSDE0612345678969789+9000000000000000000000000000001@123.COM",
                "WebSite": "www.facturaelectronica.com",
                "CodigoVendedor": "AA0000000100000000010000000002000000000300000000050000000006",
                "NumeroFacturaInterna": "123456789016",
                "NumeroPedidoInterno": "123456789016",
                "ZonaVenta": "NORTE",
                "FechaEmision": "02-04-2020"},
            "Comprador":{
                "RNCComprador": "131880681",
                "RazonSocialComprador": "DOCUMENTOS ELECTRONICOS DE 03",
                "ContactoComprador": "MARCOS LATIPLOL",
                "CorreoComprador": "MARCOSLATIPLOL@KKKK.COM",
                "DireccionComprador": "CALLE JACINTO DE LA CONCHA FELIZ ESQUINA 27 DE FEBRERO,FRENTE A DOMINO",
                "MunicipioComprador": "010100",
                "ProvinciaComprador": "010000",
                "FechaEntrega": "11-11-2020",
                "FechaOrdenCompra": "10-11-2020",
                "NumeroOrdenCompra": "4500352238",
                "CodigoInternoComprador": "10633440"},
            "InformacionesAdicionales":{
                "NumeroContenedor": "8019289",
                "NumeroReferencia": "1447"},
            "Totales":{
                "MontoExento": "400000.00",
                "MontoTotal": "400000.00"}},
        "DetallesItems": {
            "Item" : [
            {
                "NumeroLinea": 1,
                "IndicadorFacturacion": 4,
                "NombreItem": "LECHE",
                "IndicadorBienoServicio": 1,
                "CantidadItem": "10000.00",
                "UnidadMedida": "47",
                "PrecioUnitarioItem": "40.00",
                "MontoItem": "400000.00"
            }]
        },
        "InformacionReferencia":{
            "NCFModificado": "E320000000006",
            "FechaNCFModificado": "01-04-2020",
            "CodigoModificacion": "3"},
        "FechaHoraFirma": "13-12-2025 18:18:21"
    }
}